dependencytrack/__init__.py
dependencytrack/components.py
dependencytrack/exceptions.py
dependencytrack/licenses.py
dependencytrack/projects.py
dependency_track-0.0.5.dist-info/LICENSE.md
dependency_track-0.0.5.dist-info/METADATA
dependency_track-0.0.5.dist-info/WHEEL
dependency_track-0.0.5.dist-info/top_level.txt
dependency_track-0.0.5.dist-info/RECORD
