Metadata-Version: 2.1
Name: dependency-track
Version: 0.0.5
Summary: A simple wrapper for the Dependency Track REST API.
Home-page: https://github.com/alvinchchen/dependency-track-python
Author: Alvin Chen
Author-email: sonoma001@gmail.com
License: UNKNOWN
Platform: UNKNOWN
Classifier: Programming Language :: Python :: 3
Classifier: License :: OSI Approved :: GNU General Public License v2 (GPLv2)
Classifier: Operating System :: OS Independent
Requires-Python: >=3.6
